CHANGELOG.rst
MANIFEST.in
README.rst
setup.py
sqlalchemy_find.py
sqlalchemy_find.egg-info/PKG-INFO
sqlalchemy_find.egg-info/SOURCES.txt
sqlalchemy_find.egg-info/dependency_links.txt
sqlalchemy_find.egg-info/requires.txt
sqlalchemy_find.egg-info/top_level.txt