Metadata-Version: 1.1
Name: sqlalchemy-find
Version: 0.1
Summary: Syntactic sugar for SQLAlchemy: a Storm ORM-like find method
Home-page: https://bitbucket.org/ollyc/sqlalchemy-find
Author: Oliver Cope
Author-email: oliver@redgecko.org
License: BSD
Platform: UNKNOWN
Classifier: License :: OSI Approved :: Apache Software License
Classifier: Programming Language :: Python
